munotes/__init__.py
munotes/_base.py
munotes/_utils.py
munotes/chord_names.py
munotes/envelope.py
munotes/format.py
munotes/name_strings.py
munotes/notes.py
munotes/sequence.py
munotes-2.0.2.dist-info/LICENSE
munotes-2.0.2.dist-info/METADATA
munotes-2.0.2.dist-info/WHEEL
munotes-2.0.2.dist-info/top_level.txt
munotes-2.0.2.dist-info/RECORD
