Metadata-Version: 2.1
Name: munotes
Version: 2.0.2
Summary: Handle musical notes and their sounds in Python
Home-page: https://github.com/misya11p/munotes
Author: misya11p
License: MIT
Project-URL: Source, https://github.com/misya11p/munotes
Project-URL: API Reference, https://misya11p.github.io/munotes/
Keywords: music note chord sound waveform
Classifier: Development Status :: 5 - Production/Stable
Classifier: Programming Language :: Python
Classifier: Programming Language :: Python :: 3
Classifier: Programming Language :: Python :: 3 :: Only
Classifier: License :: OSI Approved :: MIT License
Requires-Python: >=3.7
License-File: LICENSE
Requires-Dist: scipy
Requires-Dist: ipython
